MANIFEST.in
README.rst
setup.py
path_pipe_conf_tools/Tools.py
path_pipe_conf_tools/__init__.py
path_pipe_conf_tools.egg-info/PKG-INFO
path_pipe_conf_tools.egg-info/SOURCES.txt
path_pipe_conf_tools.egg-info/dependency_links.txt
path_pipe_conf_tools.egg-info/top_level.txt
scripts/list-pathogen-pipeline-jobs