Metadata-Version: 1.1
Name: path-pipe-conf-tools
Version: 0.0.2
Summary: Tools for working with the pathogen pipeline at The Wellcome Trust Sanger Institute
Home-page: https://github.com/sanger-pathogens/PathPipeConfTools
Author: Ben Taylor
Author-email: ben.taylor@sanger.ac.uk
License: GPLv3
Platform: UNKNOWN
Classifier: License :: OSI Approved :: GNU General Public License v3 (GPLv3)
Classifier: Programming Language :: Python
Classifier: Development Status :: 4 - Beta
Classifier: Topic :: System :: Monitoring
Classifier: Topic :: Utilities
Classifier: Intended Audience :: Science/Research
Classifier: Topic :: Scientific/Engineering :: Bio-Informatics
